forest_rag/__init__.py
forest_rag-0.1.0.dist-info/licenses/LICENSE
forest_rag-0.1.0.dist-info/METADATA
forest_rag-0.1.0.dist-info/WHEEL
forest_rag-0.1.0.dist-info/top_level.txt
forest_rag-0.1.0.dist-info/RECORD
