Metadata-Version: 2.4
Name: forest-rag
Version: 0.1.0
Summary: A minimal ForestRAG package
Author: Oteme
Author-email: reisuzawa.0725@gmail.com
License: MIT
Requires-Python: >=3.7
License-File: LICENSE
Dynamic: license-file
